uniparser_ossetic/__init__.py
uniparser_ossetic/data_nodiacritics/__init__.py
uniparser_ossetic/data_nodiacritics/bad_analyses.txt
uniparser_ossetic/data_nodiacritics/clitics.txt
uniparser_ossetic/data_nodiacritics/derivations.txt
uniparser_ossetic/data_nodiacritics/lexemes.txt
uniparser_ossetic/data_nodiacritics/paradigms.txt
uniparser_ossetic/data_strict/__init__.py
uniparser_ossetic/data_strict/bad_analyses.txt
uniparser_ossetic/data_strict/clitics.txt
uniparser_ossetic/data_strict/derivations.txt
uniparser_ossetic/data_strict/lexemes.txt
uniparser_ossetic/data_strict/paradigms.txt
uniparser_ossetic-2.0.0.dist-info/LICENSE
uniparser_ossetic-2.0.0.dist-info/METADATA
uniparser_ossetic-2.0.0.dist-info/WHEEL
uniparser_ossetic-2.0.0.dist-info/top_level.txt
uniparser_ossetic-2.0.0.dist-info/RECORD
