Metadata-Version: 2.1
Name: uniparser-ossetic
Version: 2.0.0
Summary: Rule-based morphological analysis for Ossetic (Iron)
Home-page: https://github.com/timarkh/uniparser-grammar-ossetic
Author: Timofey Arkhangelskiy
Author-email: timarkh@gmail.com
Project-URL: Bug Tracker, https://github.com/timarkh/uniparser-grammar-ossetic/issues
Classifier: Programming Language :: Python :: 3
Classifier: License :: OSI Approved :: MIT License
Classifier: Operating System :: OS Independent
Classifier: Intended Audience :: Science/Research
Classifier: Topic :: Text Processing :: Linguistic
Requires-Python: >=3.7
License-File: LICENSE
Requires-Dist: uniparser-morph (>=2.7.2)
Requires-Dist: importlib-resources
